khl/__init__.py
khl/preprocess.py
khl/stop_words.py
khl/teams_orgs.py
khl/utils.py
khl/wrong_lemmas.py
khl-2.0.2.dist-info/WHEEL
khl-2.0.2.dist-info/METADATA
khl-2.0.2.dist-info/LICENSE
khl-2.0.2.dist-info/RECORD
