Metadata-Version: 2.1
Name: khl
Version: 2.0.2
Summary: Preparing russian hockey news for machine learning
Home-page: https://github.com/Rishat-F/khl
License: MIT
Keywords: khl,news,nlp,preprocessing,ml
Author: Rishat Fayzullin
Author-email: nilluziaf@gmail.com
Requires-Python: >=3.8,<4.0
Classifier: License :: OSI Approved :: MIT License
Classifier: Programming Language :: Python :: 3
Classifier: Programming Language :: Python :: 3.8
Classifier: Programming Language :: Python :: 3.9
Classifier: Programming Language :: Python :: 3.10
Classifier: Programming Language :: Python :: 3.11
Requires-Dist: natasha (==1.4.0)
Project-URL: Repository, https://github.com/Rishat-F/khl
